lite_bootstrap/__init__.py
lite_bootstrap/bootstrappers/__init__.py
lite_bootstrap/bootstrappers/base.py
lite_bootstrap/bootstrappers/fastapi_bootstrapper.py
lite_bootstrap/bootstrappers/faststream_bootstrapper.py
lite_bootstrap/bootstrappers/free_bootstrapper.py
lite_bootstrap/bootstrappers/litestar_bootstrapper.py
lite_bootstrap/helpers/__init__.py
lite_bootstrap/helpers/fastapi_helpers.py
lite_bootstrap/helpers/path.py
lite_bootstrap/import_checker.py
lite_bootstrap/instruments/__init__.py
lite_bootstrap/instruments/base.py
lite_bootstrap/instruments/cors_instrument.py
lite_bootstrap/instruments/healthchecks_instrument.py
lite_bootstrap/instruments/logging_instrument.py
lite_bootstrap/instruments/opentelemetry_instrument.py
lite_bootstrap/instruments/prometheus_instrument.py
lite_bootstrap/instruments/sentry_instrument.py
lite_bootstrap/instruments/swagger_instrument.py
lite_bootstrap/py.typed
lite_bootstrap/static/fastapi_docs/redoc.standalone.js
lite_bootstrap/static/fastapi_docs/swagger-ui-bundle.js
lite_bootstrap/static/fastapi_docs/swagger-ui.css
lite_bootstrap/static/litestar_docs/asyncapi-web-component.js
lite_bootstrap/static/litestar_docs/default.min.css
lite_bootstrap/static/litestar_docs/swagger-ui-bundle.js
lite_bootstrap/static/litestar_docs/swagger-ui-standalone-preset.js
lite_bootstrap/static/litestar_docs/swagger-ui.css
lite_bootstrap/types.py
lite_bootstrap-0.24.0.dist-info/WHEEL
lite_bootstrap-0.24.0.dist-info/METADATA
lite_bootstrap-0.24.0.dist-info/RECORD
